LICENSE
MANIFEST.in
README.md
package.json
setup.py
dash_fullscreen/DashFullscreen.py
dash_fullscreen/__init__.py
dash_fullscreen/_imports_.py
dash_fullscreen/dash_fullscreen.min.js
dash_fullscreen/dash_fullscreen.min.js.map
dash_fullscreen/metadata.json
dash_fullscreen/package-info.json
dash_fullscreen.egg-info/PKG-INFO
dash_fullscreen.egg-info/SOURCES.txt
dash_fullscreen.egg-info/dependency_links.txt
dash_fullscreen.egg-info/top_level.txt
tests/test_usage.py