Metadata-Version: 2.1
Name: dash-fullscreen
Version: 0.0.2
Summary: Project Description
Author: mapix <mapix.me@gmail.com>
License: MIT
Classifier: Framework :: Dash
License-File: LICENSE
